[
    {
        "id": 1,
        "first_name": "Hyacinthie",
        "last_name": "Whyffen",
        "dob": "2001/01/04",
        "rate": "up"
    },
    {
        "id": 2,
        "first_name": "Yettie",
        "last_name": "Mattevi",
        "dob": "1991/10/30",
        "rate": "up"
    },
    {
        "id": 3,
        "first_name": "Klaus",
        "last_name": "Juppe",
        "dob": "1999/07/31",
        "rate": "down"
    },
    {
        "id": 4,
        "first_name": "Corbet",
        "last_name": "Brigge",
        "dob": "1982/09/14",
        "rate": "up"
    },
    {
        "id": 5,
        "first_name": "Colas",
        "last_name": "Mulvany",
        "dob": "1992/05/05",
        "rate": "down"
    },
    {
        "id": 6,
        "first_name": "Noble",
        "last_name": "Tonkin",
        "dob": "1986/03/20",
        "rate": "up"
    },
    {
        "id": 7,
        "first_name": "Emory",
        "last_name": "Hansie",
        "dob": "2001/11/15",
        "rate": "up"
    },
    {
        "id": 8,
        "first_name": "Dunstan",
        "last_name": "Emerine",
        "dob": "1985/06/04",
        "rate": "up"
    },
    {
        "id": 9,
        "first_name": "Rhys",
        "last_name": "Gaudin",
        "dob": "2014/02/22",
        "rate": "up"
    },
    {
        "id": 10,
        "first_name": "Maggie",
        "last_name": "Canner",
        "dob": "2012/02/21",
        "rate": "down"
    },
    {
        "id": 11,
        "first_name": "Mag",
        "last_name": "Scoyne",
        "dob": "2013/05/14",
        "rate": "up"
    },
    {
        "id": 12,
        "first_name": "Gates",
        "last_name": "Kilty",
        "dob": "2005/08/04",
        "rate": "up"
    },
    {
        "id": 13,
        "first_name": "Dukie",
        "last_name": "Erricker",
        "dob": "1997/04/04",
        "rate": "up"
    },
    {
        "id": 14,
        "first_name": "Kim",
        "last_name": "Behr",
        "dob": "1991/12/06",
        "rate": "up"
    },
    {
        "id": 15,
        "first_name": "Ardyce",
        "last_name": "Cristoforo",
        "dob": "2003/05/30",
        "rate": "up"
    },
    {
        "id": 16,
        "first_name": "Hedwiga",
        "last_name": "Penwright",
        "dob": "1982/11/13",
        "rate": "up"
    },
    {
        "id": 17,
        "first_name": "Sidnee",
        "last_name": "Dawney",
        "dob": "1995/11/14",
        "rate": "down"
    },
    {
        "id": 18,
        "first_name": "Miguela",
        "last_name": "Keling",
        "dob": "2015/07/10",
        "rate": "down"
    },
    {
        "id": 19,
        "first_name": "Filippo",
        "last_name": "Hartley",
        "dob": "2000/05/30",
        "rate": "down"
    },
    {
        "id": 20,
        "first_name": "Starr",
        "last_name": "Urlich",
        "dob": "2017/04/05",
        "rate": "down"
    },
    {
        "id": 21,
        "first_name": "Tedda",
        "last_name": "Sivorn",
        "dob": "2001/02/18",
        "rate": "up"
    },
    {
        "id": 22,
        "first_name": "Berta",
        "last_name": "Shewery",
        "dob": "1987/12/14",
        "rate": "down"
    },
    {
        "id": 23,
        "first_name": "Wileen",
        "last_name": "Vegas",
        "dob": "1998/11/11",
        "rate": "up"
    },
    {
        "id": 24,
        "first_name": "Margarita",
        "last_name": "Clapshaw",
        "dob": "2010/06/05",
        "rate": "up"
    },
    {
        "id": 25,
        "first_name": "Norean",
        "last_name": "Vannoni",
        "dob": "2013/07/14",
        "rate": "down"
    }
]